MANIFEST.in
README.rst
bootstrap.py
buildout.cfg
pipeline.cfg
setup.py
docs/HISTORY.txt
docs/sample_content/index.html
docs/sample_content/augue/index.html
docs/sample_content/gravida/index.html
docs/sample_content/hac/index.html
docs/sample_content/non/index.html
docs/sample_content/orci/index.html
docs/sample_content/placerat/index.html
docs/sample_content/posuere/index.html
docs/sample_content/venenatis/index.html
docs/sample_content/vulputate/index.html
transmogrify/__init__.py
transmogrify.extract.egg-info/PKG-INFO
transmogrify.extract.egg-info/SOURCES.txt
transmogrify.extract.egg-info/dependency_links.txt
transmogrify.extract.egg-info/entry_points.txt
transmogrify.extract.egg-info/namespace_packages.txt
transmogrify.extract.egg-info/requires.txt
transmogrify.extract.egg-info/top_level.txt
transmogrify/extract/__init__.py
transmogrify/extract/configure.zcml