Metadata-Version: 1.0
Name: transmogrify.extract
Version: 0.4.0
Summary: Extracts all content from within the specified CSS id
Home-page: https://github.com/aclark4life/transmogrify.extract
Author: Alex Clark
Author-email: aclark@aclark.net
License: GPL
Platform: UNKNOWN
